torchid/__init__.py
torchid/datasets.py
torchid/metrics.py
torchid/dynonet/__init__.py
torchid/dynonet/filtering.py
torchid/dynonet/functional/__init__.py
torchid/dynonet/functional/lti.py
torchid/dynonet/module/__init__.py
torchid/dynonet/module/lti.py
torchid/dynonet/module/static.py
torchid/io/__init__.py
torchid/io/module/__init__.py
torchid/io/module/io_simulator.py
torchid/io/module/iomodels.py
torchid/ss/__init__.py
torchid/ss/poly_utils.py
torchid/ss/ct/__init__.py
torchid/ss/ct/models.py
torchid/ss/ct/simulators.py
torchid/ss/dt/__init__.py
torchid/ss/dt/estimators.py
torchid/ss/dt/models.py
torchid/ss/dt/simulator.py
torchid/tests/__init__.py
torchid/tests/ss_ct_test.py
pytorch_ident-0.2.5.dist-info/LICENSE
pytorch_ident-0.2.5.dist-info/METADATA
pytorch_ident-0.2.5.dist-info/WHEEL
pytorch_ident-0.2.5.dist-info/top_level.txt
pytorch_ident-0.2.5.dist-info/RECORD
